shelix/__init__.py
shelix/log_socket.py
shelix/main.py
star_helix-0.6.0.dist-info/entry_points.txt
star_helix-0.6.0.dist-info/WHEEL
star_helix-0.6.0.dist-info/METADATA
star_helix-0.6.0.dist-info/LICENSE
star_helix-0.6.0.dist-info/RECORD
