Metadata-Version: 2.1
Name: star-helix
Version: 0.6.0
Summary: Logging service client code and cli
License: MIT
Author-email: Paul Bailey <paul@cognitivespace.com>
Requires-Python: >=3.7
Requires-Dist: asynchronousfilereader
Requires-Dist: haikunator
Requires-Dist: httpx>=0.21.3
Requires-Dist: typer
Requires-Dist: websocket-client>=1.2.3
Project-URL: homepage, https://github.com/cognitive-space/star-helix
